django_simple_url/__init__.py
django_simple_url/converters.py
django_simple_url-0.0.4.dist-info/DESCRIPTION.rst
django_simple_url-0.0.4.dist-info/METADATA
django_simple_url-0.0.4.dist-info/RECORD
django_simple_url-0.0.4.dist-info/WHEEL
django_simple_url-0.0.4.dist-info/metadata.json
django_simple_url-0.0.4.dist-info/top_level.txt
