Metadata-Version: 2.0
Name: django-simple-url
Version: 0.0.4
Summary: Simpler URL specification for Django.
Home-page: https://github.com/sjoerdjob/django-simple-url
Author: Sjoerd Job Postmus
Author-email: sjoerdjob@sjec.nl
License: MIT license
Keywords: django,url
Platform: UNKNOWN
Classifier: Development Status :: 3 - Alpha
Classifier: Framework :: Django
Classifier: Intended Audience :: Developers
Classifier: License :: OSI Approved :: MIT License
Classifier: Natural Language :: English
Classifier: Operating System :: OS Independent
Classifier: Programming Language :: Python :: 2
Classifier: Programming Language :: Python :: 2.7
Classifier: Programming Language :: Python :: 3
Classifier: Programming Language :: Python :: 3.4
Classifier: Programming Language :: Python :: 3.5
